cyfaust/CMakeLists.txt
cyfaust/__init__.py
cyfaust/__main__.py
cyfaust/cyfaust.cpython-310-x86_64-linux-gnu.so
cyfaust/resources/architecture/alsa-console.cpp
cyfaust/resources/architecture/alsa-gtk.cpp
cyfaust/resources/architecture/alsa-qt.cpp
cyfaust/resources/architecture/au-effect.cpp
cyfaust/resources/architecture/au-instrument.cpp
cyfaust/resources/architecture/bench.cpp
cyfaust/resources/architecture/c-jack-gtk.c
cyfaust/resources/architecture/ca-gtk.cpp
cyfaust/resources/architecture/ca-qt.cpp
cyfaust/resources/architecture/cpal.rs
cyfaust/resources/architecture/csound.cpp
cyfaust/resources/architecture/csvplot.cpp
cyfaust/resources/architecture/dssi.cpp
cyfaust/resources/architecture/dummy-mem.cpp
cyfaust/resources/architecture/dummy.cpp
cyfaust/resources/architecture/faustvst.cpp
cyfaust/resources/architecture/faustvstqt.h
cyfaust/resources/architecture/gen-json.cpp
cyfaust/resources/architecture/jack-console.cpp
cyfaust/resources/architecture/jack-gtk-ros.cpp
cyfaust/resources/architecture/jack-gtk.cpp
cyfaust/resources/architecture/jack-internal.cpp
cyfaust/resources/architecture/jack-qt-chain-footer.cpp
cyfaust/resources/architecture/jack-qt-chain-header.cpp
cyfaust/resources/architecture/jack-qt.cpp
cyfaust/resources/architecture/jack.rs
cyfaust/resources/architecture/ladspa.cpp
cyfaust/resources/architecture/latexheader.tex
cyfaust/resources/architecture/lv2.cpp
cyfaust/resources/architecture/lv2qtgui.h
cyfaust/resources/architecture/lv2ui.cpp
cyfaust/resources/architecture/minimal-bench.cpp
cyfaust/resources/architecture/minimal-effect.c
cyfaust/resources/architecture/minimal-effect.cpp
cyfaust/resources/architecture/minimal-fixed-point.cpp
cyfaust/resources/architecture/minimal-static.cpp
cyfaust/resources/architecture/minimal.c
cyfaust/resources/architecture/minimal.cpp
cyfaust/resources/architecture/minimal.rs
cyfaust/resources/architecture/module.cpp
cyfaust/resources/architecture/octave.cpp
cyfaust_llvm-0.1.1.dist-info/METADATA
cyfaust_llvm-0.1.1.dist-info/WHEEL
cyfaust_llvm-0.1.1.dist-info/entry_points.txt
cyfaust_llvm-0.1.1.dist-info/RECORD
cyfaust_llvm-0.1.1.dist-info/licenses/LICENSE
cyfaust_llvm-0.1.1.dist-info/sboms/auditwheel.cdx.json
