Metadata-Version: 2.4
Name: cyfaust-llvm
Version: 0.1.1
Summary: A Cython wrapper of the Faust interpreter and signal processing library with RtAudio support.
Keywords: faust,dsp,audio,signal-processing,music,sound,synthesis,cython,rtaudio,real-time
Author-Email: Shakeeb Alireza <shakfu@users.noreply.github.com>
Maintainer-Email: Shakeeb Alireza <shakfu@users.noreply.github.com>
License-Expression: MIT
Classifier: Development Status :: 3 - Alpha
Classifier: Intended Audience :: Developers
Classifier: Intended Audience :: Science/Research
Classifier: Operating System :: MacOS
Classifier: Operating System :: Microsoft :: Windows
Classifier: Operating System :: POSIX :: Linux
Classifier: Programming Language :: Cython
Classifier: Programming Language :: Python :: 3
Classifier: Programming Language :: Python :: 3.10
Classifier: Programming Language :: Python :: 3.11
Classifier: Programming Language :: Python :: 3.12
Classifier: Programming Language :: Python :: 3.13
Classifier: Programming Language :: Python :: 3.14
Classifier: Programming Language :: Python :: Implementation :: CPython
Classifier: Topic :: Multimedia :: Sound/Audio
Classifier: Topic :: Multimedia :: Sound/Audio :: Sound Synthesis
Classifier: Topic :: Multimedia :: Sound/Audio :: Analysis
Classifier: Topic :: Scientific/Engineering
Classifier: Topic :: Software Development :: Libraries :: Python Modules
Classifier: Typing :: Typed
Project-URL: Homepage, https://github.com/shakfu/cyfaust
Project-URL: Repository, https://github.com/shakfu/cyfaust
Project-URL: Documentation, https://github.com/shakfu/cyfaust#readme
Project-URL: Issues, https://github.com/shakfu/cyfaust/issues
Project-URL: Changelog, https://github.com/shakfu/cyfaust/blob/main/CHANGELOG.md
Requires-Python: >=3.10
